Workbook

Sheet Balises
A1: Région | B1: Département | C1: Dépt | D1: N° | E1: Balise | F1: Réseau | G1: Statut | H1: Alt. balise (m) | I1: Lien balise | J1: Lat | K1: Lon | L1: Spot le plus proche (<5 km) | M1: Dist. (km) | N1: Vent idéal | O1: Vent possible | P1: Alt. déco (m) | Q1: Alt. atterro (m) | R1: D+ (m) | S1: Atterrissage | T1: Therm. | U1: Soar. | V1: Treuil | W1: Règles / restrictions | X1: Météo & pièges | Y1: Remarques | Z1: Accès | AA1: Fiche Paragliding Earth | AB1: Note balise (club)
A2: Alsace | B2: Bas Rhin | C2: 67 | D2: 1007 | E2: Altenberg | F2: Holfuy | G2: OK | H2: 880 | I2: https://www.balisemeteo.com/balise.php?idBalise=1007 | J2: 48.2954 | K2: 7.3128 | L2: Altenberg - rocher du coucou | M2: 0.38 | N2: NE | O2: N | P2: 300 | Q2: 759 | T2: oui | U2: oui | W2: MAX ALTITUDE : 1500M_x000D_ OPEN ONLY FROM MARCH 1st TO OCTOBER 31st_x000D_ http://lavl.free.fr/paragliding-vosges.html_x000D_ http://lavl.free.fr/Espace-Aerien-Vosges.html | AA2: http://www.paraglidingearth.com/?site=2941 | AB2: Balise du site Altenberg - Rocher du Coucou Le vent d'un large secteur W n'est pas pertinent, l'anémomètre est déventé par l'antenne sur laquelle il est fixé.
A3: Alsace | B3: Bas Rhin | C3: 67 | D3: 2061 | E3: Avolsheim | F3: Openwindmap | G3: OK | H3: 167 | I3: https://www.balisemeteo.com/balise.php?idBalise=2061 | J3: 48.557077 | K3: 7.515378 | L3: aucun à <5 km
A4: Alsace | B4: Bas Rhin | C4: 67 | D4: 2560 | E4: Base ULM de Batzendorf | F4: Openwindmap | G4: OK | H4: 200 | I4: https://www.balisemeteo.com/balise.php?idBalise=2560 | J4: 48.802633 | K4: 7.727189 | L4: aucun à <5 km
A5: Alsace | B5: Bas Rhin | C5: 67 | D5: 74 | E5: Breitenbach | F5: Adison | G5: OK | H5: 948 | I5: https://www.balisemeteo.com/balise.php?idBalise=74 | J5: 48.3839 | K5: 7.28301 | L5: Breitenbach-Pelage | M5: 0.04 | N5: SE·S | O5: E·SW | P5: 934 | Q5: 436 | R5: 498 | T5: oui | Y5: Do'nt fly ower 1350m, limit of TMA!_x000D_ _x000D_ Official informations:_x000D_ http://www.grandvol.com/site.htm#Carte | AA5: http://www.paraglidingearth.com/?site=2944 | AB5: <u><b>ATTENTION :</b></u></br> </br> - Le site est proche de la CTR de Strasbourg et se trouve sous deux espaces aériens contigus : Plafonds 1350m et 1500m à respecter.</br> </br> - une <b>PTU</b> coté village est <b><u>obligatoire</u></b> en approche du terrain d'atterrissage</br> </br> - Orientations: Sud-Est et Sud-Ouest
A6: Alsace | B6: Bas Rhin | C6: 67 | D6: 5000 | E6: Eckbolsheim | F6: — | G6: OK | H6: 144 | I6: https://www.balisemeteo.com/balise.php?idBalise=5000 | J6: 48.575568 | K6: 7.686625 | L6: aucun à <5 km | AB6: Balise située à Eckbolsheim, dégagée bien au vent d'Ouest<br> Bien représentative des conditions possibles<br> Pour le site de Mundolsheim<br> (capteur à ultrtasons à 10m / sol)
A7: Alsace | B7: Bas Rhin | C7: 67 | D7: 5001 | E7: Grendelbruch | F7: — | G7: En maintenance | H7: 753 | I7: https://www.balisemeteo.com/balise.php?idBalise=5001 | J7: 48.4925 | K7: 7.32306 | L7: Schwartzbach | M7: 3.1 | N7: N·NE·NW | P7: 462 | Q7: 284 | R7: 178 | T7: oui | W7: TMA at 1520m, don't fly higher !_x000D_ Don't fly when sheep are there ! | AA7: http://www.paraglidingearth.com/?site=2943
A8: Alsace | B8: Bas Rhin | C8: 67 | D8: 5002 | E8: J9 | F8: — | G8: OK | H8: 188 | I8: https://www.balisemeteo.com/balise.php?idBalise=5002 | J8: 48.6217 | K8: 7.68361 | L8: Mundolsheim | M8: 1.65 | N8: NW | O8: N·W | P8: 155 | U8: oui | W8: UNDER TMA STRASBOURG_x000D_ MAXIMAL ALTITUDE 150 METERS ABOVE GROUND, ca 300 METERS ABOVE SEA | X8: Wind can become stronger. Don't fly direct above the ridge. _x000D_ Do not train close to the ridge, risks of unwanted take off ! | Y8: Not for beginners. There is always 25-30 kmh wind. You have to be proficient in strong wind reverse takeoffs. | Z8: 15km NW from Strasbourg_x000D_ Colline de Mittelhausbergen | AA8: http://www.paraglidingearth.com/?site=6936 | AB8: Balise associée au site de vol de Mundolsheim. En maintenance (panneau solaire obstrué par végétation)
A9: Alsace | B9: Bas Rhin | C9: 67 | D9: 5095 | E9: Lauf (D) | F9: Holfuy | G9: OK | H9: 800 | I9: https://www.balisemeteo.com/balise.php?idBalise=5095 | J9: 48.62498 | K9: 8.16251 | L9: Sodkopf | M9: 0.03 | N9: W | O9: SW·NW | P9: 775 | Q9: 294 | R9: 481 | T9: oui | AA9: http://www.paraglidingearth.com/?site=8764
A10: Alsace | B10: Bas Rhin | C10: 67 | D10: 3333 | E10: Merkur | F10: Openwindmap | G10: En maintenance | H10: 637 | I10: https://www.balisemeteo.com/balise.php?idBalise=3333 | J10: 48.764437 | K10: 8.280852 | L10: Merkur | M10: 0.11 | N10: NE·SW·W | O10: S | P10: 651 | Q10: 254 | R10: 397 | S10: Landing zone | T10: oui | U10: oui | W10: West: 1. Read the website 2. Inspect LZ before taking the cable car 3. Take the cable car, purchase a "Flieg auf und ab" ticket. This includes the guest site fee for the day. For subsequent flights on the same day, a single "up" ticket is sufficient. Don't use your own car. 4. Ask a local for a briefing. This is mandatory, as we will get in trouble if you crash and we are unable to provide proof that you got a briefing to the police. North East: Boils down to locals only, see website. | X10: See https://www.schwarzwaldgeier.de/wetterstation-merkur/ for the current situation. Local wind is often a good deal stronger than meteo wind. Perfect groundhandling skills are a must. | Y10: Crowded on weekends. XC is usually one-way downwind to the east. | Z10: Cable car or walking. DO NOT drive to the takeoff. The cable car runs from 10 a.m. to 10 p.m. (!) every 5 minutes and is rather low priced. Don't use the vending machine, but the ticket window to grant the lady her commision (no additional cost for you). After purchasing, don't use the tourist queue, but the greenish door to the left. Go to the upper end of the stairs to be out of the way for the tourists leaving the car once it arrives. This means you will be cutting in line. Please make up for that by standing and leaving the seats to the tourists, or, if it's really crowded, skip the first car. The next one will arrive just 5 minutes later. http://www.stadtwerke-baden-baden.de/merkur-bergbahn/ | AA10: http://www.paraglidingearth.com/?site=8662
A11: Alsace | B11: Bas Rhin | C11: 67 | D11: 45 | E11: Reinhardsmunster | F11: Adison | G11: OK | H11: 506 | I11: https://www.balisemeteo.com/balise.php?idBalise=45 | J11: 48.677502 | K11: 7.3119402 | L11: Reinhardsmunster | M11: 0 | N11: NE·E·SE | P11: 526 | Q11: 324 | R11: 202 | T11: oui | U11: oui | W11: Airspace during the weekdays: YOU MUST contact the Phalsbourg airbase (Tél. 03 87 25 21 53) !!! if you are the fist OR last to fly/land!!! see airspace image in the PHOTOS. Do not take off after 30 minutes prior to sunset. In september (ususally the whole month) the site is CLOSED due to the "Brame du Cerf" the annual deer breeding time. Check with the local pilots and/or contact numbers on the Flying site information pannel (on the takeoff and landing). | X11: Take off a very technical, can be dangerous, in strong wind. Magic lift fenomenon on some days in the evening. | Y11: XC to Haut Barr castle (up north) is a classic._x000D_ _x000D_ Max. height : 1520m_x000D_ _x000D_ Flights are NOT ALLOWED from monday 06h00 friday 15h00 (military zone)._x000D_ _x000D_ Access to the site is strictly FORBIDDEN in September (deers fornication ...). | AA11: http://www.paraglidingearth.com/?site=2946
A12: Alsace | B12: Bas Rhin | C12: 67 | D12: 2638 | E12: Rohrbach | F12: Openwindmap | G12: OK | H12: 371 | I12: https://www.balisemeteo.com/balise.php?idBalise=2638 | J12: 49.043964 | K12: 7.251931 | L12: aucun à <5 km
A13: Alsace | B13: Bas Rhin | C13: 67 | D13: 5010 | E13: Strasbourg | F13: — | G13: OK | H13: 144 | I13: https://www.balisemeteo.com/balise.php?idBalise=5010 | J13: 48.575568 | K13: 7.686625 | L13: aucun à <5 km | AB13: Balise située à Strasbourg au sommet de la place des Halles (95m AGL)<br> Bien représentative des conditions possibles<br> Pour le site de Mundolsheim<br> (capteur à ultrtasons)
A14: Alsace | B14: Haut Rhin | C14: 68 | D14: 2829 | E14: ACO Cernay | F14: Openwindmap | G14: OK | H14: 279 | I14: https://www.balisemeteo.com/balise.php?idBalise=2829 | J14: 47.8112 | K14: 7.201219 | L14: aucun à <5 km
A15: Alsace | B15: Haut Rhin | C15: 68 | D15: 5015 | E15: Brezouard | F15: Holfuy | G15: OK | H15: 1188 | I15: https://www.balisemeteo.com/balise.php?idBalise=5015 | J15: 48.1889 | K15: 7.1500001 | L15: Ribeaugoutte | M15: 1.34 | N15: NE | P15: 1050 | W15: http://lavl.free.fr/paragliding-vosges.html_x000D_ http://lavl.free.fr/Espace-Aerien-Vosges.html | AA15: http://www.paraglidingearth.com/?site=2954 | AB15: Cette balise est représentative en direction et force du flux pour les sites suivants : Surcenord, Ribeaugoutte, Bonhomme, Haicot, Fille Morte. Webcam : https://holfuy.com/fr/camera/898
A16: Alsace | B16: Haut Rhin | C16: 68 | D16: 5016 | E16: Gaschney | F16: Openwindmap | G16: OK | H16: 1278 | I16: https://www.balisemeteo.com/balise.php?idBalise=5016 | J16: 48.035022 | K16: 7.0347385 | L16: Le gaschney | M16: 0.07 | N16: S·W | P16: 1258 | Y16: No intermediary landing zone !!!_x000D_ Be careful, landing quite far from take off. | AA16: http://www.paraglidingearth.com/?site=2958 | AB16: Mise en service 06/06/26.
A17: Alsace | B17: Haut Rhin | C17: 68 | D17: 3418 | E17: La Soulce | F17: Openwindmap | G17: OK | H17: 967 | I17: https://www.balisemeteo.com/balise.php?idBalise=3418 | J17: 47.310748 | K17: 7.290744 | L17: Montagne de Moutier | M17: 4.02 | N17: SE | P17: 1080 | T17: oui | Y17: Airspaces in Switzerland are a thought subject. Get all the info you can before flying by visiting http://www.vollibrejura.ch. | AA17: http://www.paraglidingearth.com/?site=7971
A18: Alsace | B18: Haut Rhin | C18: 68 | D18: 5013 | E18: Petit Ballon | F18: — | G18: OK | H18: 1270 | I18: https://www.balisemeteo.com/balise.php?idBalise=5013 | J18: 47.980801 | K18: 7.12567 | L18: aucun à <5 km | AB18: La balise est située au sommet du Petit Ballon à 1272 mètres dégagée de tout obstacle à tous azimuts.
A19: Alsace | B19: Haut Rhin | C19: 68 | D19: 2929 | E19: Schnepfenried | F19: Openwindmap | G19: OK | H19: 1245 | I19: https://www.balisemeteo.com/balise.php?idBalise=2929 | J19: 47.978525 | K19: 7.043083 | L19: Schnepfenried | M19: 0.09 | N19: NE·E | P19: 1221 | Q19: 604 | R19: 617 | T19: oui | U19: oui | X19: Good site the morning until 12h00. | Y19: Restricted Airspace, _x000D_ see http://lavl.free.fr/paragliding-vosges.html | Z19: From road D27 from Munster to road 68 to the | AA19: http://www.paraglidingearth.com/?site=2950 | AB19: Pile neuve Avril 2026
A20: Alsace | B20: Haut Rhin | C20: 68 | D20: 6005 | E20: Tertre Fille Morte | F20: Holfuy | G20: OK | H20: 1050 | I20: https://www.balisemeteo.com/balise.php?idBalise=6005 | J20: 48.2189 | K20: 7.1934 | L20: aucun à <5 km
A21: Alsace | B21: Haut Rhin | C21: 68 | D21: 5085 | E21: Thanner Hubel | F21: — | G21: OK | H21: 1150 | I21: https://www.balisemeteo.com/balise.php?idBalise=5085 | J21: 47.824461 | K21: 7.024826 | L21: aucun à <5 km | AB21: <h2>Mises en garde</h2> <b>Attention</b>, aux indications et aux conditions trompeuses : la balise se situe sur le flanc Est du massif et complètement sous le vent d'Ouest.<br><br> Décollage toléré, non officiel possible, niveau marron conseillé et requis, sur le haut de la chaume, à droite du dernier pylône de la remontée mécanique.<br><br> <b>Attention</b> : accès voiture interdit. Garez-vous au parking (1km plus bas) ou mieux encore, montez à pieds depuis la vallée ou depuis le col du Hundsbruck.<br><br> <b>Attention</b>, les premières prairies atterrissables sont interdites par arrêté municipal et ne sont pas en finesse en l'absence de brise et en présence de vent météo face.
A22: Alsace | B22: Haut Rhin | C22: 68 | D22: 136 | E22: Treh - Markstein | F22: Adison | G22: OK | H22: 1262 | I22: https://www.balisemeteo.com/balise.php?idBalise=136 | J22: 47.926899 | K22: 7.01722 | L22: Treh markstein | M22: 0.42 | N22: SW·W | O22: S·NW | P22: 1227 | Q22: 444 | R22: 783 | T22: oui | U22: oui | W22: http://lavl.free.fr/paragliding-vosges.html :Vosges Airspace Areas_x000D_ or in french with maps : http://lavl.free.fr/Espace-Aerien-Vosges.html | Y22: Be carefull with local airspace rules (airport near) | Z22: Here you can find the official informations and map:_x000D_ http://lavl.free.fr/site-parapente-vosges/SitesValleeThur.html | AA22: http://www.paraglidingearth.com/?site=2959 | AB22: Pas de gonflage ni de pliage sur le dôme (seule la repose au sommet est tolérée). Dégagez la chaumes la voile en boule par le chemin le plus court en rejoignant le sentier de randonnée.
A23: Aquitaine | B23: Dordogne | C23: 24 | D23: 3411 | E23: Aubas | F23: Openwindmap | G23: OK | H23: 200 | I23: https://www.balisemeteo.com/balise.php?idBalise=3411 | J23: 45.08852 | K23: 1.215125 | L23: Aubas | M23: 0.01 | N23: N | O23: NE·NW | P23: 203 | Q23: 80 | R23: 123 | AA23: http://www.paraglidingearth.com/?site=2686
A24: Aquitaine | B24: Dordogne | C24: 24 | D24: 2185 | E24: Coubjours | F24: Openwindmap | G24: En maintenance | H24: 195 | I24: https://www.balisemeteo.com/balise.php?idBalise=2185 | J24: 45.088753 | K24: 1.215725 | L24: Aubas | M24: 0.05 | N24: N | O24: NE·NW | P24: 203 | Q24: 80 | R24: 123 | AA24: http://www.paraglidingearth.com/?site=2686
A25: Aquitaine | B25: Dordogne | C25: 24 | D25: 2828 | E25: Côte de Jor 222m | F25: Openwindmap | G25: OK | H25: 221 | I25: https://www.balisemeteo.com/balise.php?idBalise=2828 | J25: 45.017214 | K25: 1.070796 | L25: St leon sur vezere | M25: 0.02 | N25: SE | P25: 228 | Q25: 228 | AA25: http://www.paraglidingearth.com/?site=2685
A26: Aquitaine | B26: Dordogne | C26: 24 | D26: 2143 | E26: St Léon sur Vézère | F26: Openwindmap | G26: En maintenance | H26: 221 | I26: https://www.balisemeteo.com/balise.php?idBalise=2143 | J26: 45.017288 | K26: 1.070672 | L26: St leon sur vezere | M26: 0.01 | N26: SE | P26: 228 | Q26: 228 | AA26: http://www.paraglidingearth.com/?site=2685
A27: Aquitaine | B27: Gironde | C27: 33 | D27: 2415 | E27: Plages du Crohot et du Porge | F27: Openwindmap | G27: En maintenance | H27: 18 | I27: https://www.balisemeteo.com/balise.php?idBalise=2415 | J27: 44.841316 | K27: -1.225446 | L27: aucun à <5 km | AB27: Pioupiou placé en haut de la dune entre les plages du Crohot et du Porge.
A28: Aquitaine | B28: Gironde | C28: 33 | D28: 64 | E28: Pyla Pilat | F28: Adison | G28: OK | H28: 55 | I28: https://www.balisemeteo.com/balise.php?idBalise=64 | J28: 44.576111 | K28: -1.2247222 | L28: Dune de Pilat | M28: 0.45 | N28: W·NW | P28: 50 | T28: oui | U28: oui | W28: It's very busy in Summer but so fun all the Time | Y28: The Fisrt International Competition of Paragliding directly in the Sand !_x000D_ http://www.wagas-festival.com/_x000D_ or here http://www.parateam.com/_x000D_ You have an smashing video here from 'the king of the dune's' :_x000D_ http://pyal.ifrance.com/cariboost1/ | AA28: http://www.paraglidingearth.com/?site=7217 | AB28: PIÉTINEMENT des OYATS INTERDIT (protection dunaire). Casque et accélérateur obligatoires (risque de reculade au-delà de 25 Km/h). VOL à "La Corniche" (Nord Dune) INTERDIT du 1/04 au 15/11 (Arrêté municipal).
A29: Aquitaine | B29: Lot et Garonne | C29: 47 | D29: 165 | E29: Pech de Berre | F29: Adison | G29: OK | H29: 107 | I29: https://www.balisemeteo.com/balise.php?idBalise=165 | J29: 44.3242 | K29: 0.34916699 | L29: Nicole | M29: 0.18 | N29: NE·SW | O29: E·W | P29: 149 | Q29: 32 | R29: 117 | T29: oui | U29: oui | Y29: Be careful in the air not to fly into the cross. | AA29: http://www.paraglidingearth.com/?site=2838
A30: Aquitaine | B30: Lot et Garonne | C30: 47 | D30: 2906 | E30: Penne d'Agenais | F30: Openwindmap | G30: OK | H30: 219 | I30: https://www.balisemeteo.com/balise.php?idBalise=2906 | J30: 44.390455 | K30: 0.823063 | L30: Penne d\'agenais | M30: 0.09 | N30: N·NW | O30: NE | P30: 197 | Q30: 58 | R30: 139 | T30: oui | U30: oui | Z30: To get there, follow the signs for 'penne d'a' untill you reach the top of the road, park at the entrance of the village. | AA30: http://www.paraglidingearth.com/?site=2836 | AB30: Recommandations : Orientations favorables du vent : Nord-ouest à Nord. Décollage idéal : face voile puis monter sur la butte avant le décollage. (Ne pas monter au sommet de la butte) Le décollage est favorisé par l’arrivée d’un thermique modéré. Conseil : Découvrir le site avec un adhérent du club. A éviter : -décollage sans vent (mini : 10 km/h) -Décollage par vents forts (>25km/h) -Directions du vent en dehors des orientations favorables Danger : effet venturi possible entre le terrain de décollage et la basilique (au dessus du village). Terrain d’atterrissage : attention à la ligne de chemin de fer au sud du terrain, présence d’une ligne électrique. Ne pas survoler la maison à l’est du terrain, risque de gradient à l’arrivée qui augmente le taux de chute.
A31: Aquitaine | B31: Pyrénées Atlantiques | C31: 64 | D31: 138 | E31: Accous | F31: Adison | G31: OK | H31: 1590 | I31: https://www.balisemeteo.com/balise.php?idBalise=138 | J31: 43.024399 | K31: -0.65444398 | L31: Le Layens | M31: 0.91 | N31: S | P31: 1518 | AA31: http://www.paraglidingearth.com/?site=2921 | AB31: La balise du Layens est dégagé de tous reliefs, et, est sous l'influence du vent météo. Le versant sud peut donner des vitesses de brises de pente faibles lors de vent météo nul.
A32: Aquitaine | B32: Pyrénées Atlantiques | C32: 64 | D32: 43 | E32: Baigura | F32: Openwindmap | G32: OK | H32: 838 | I32: https://www.balisemeteo.com/balise.php?idBalise=43 | J32: 43.294601 | K32: -1.28878 | L32: Baigura | M32: 0.28 | N32: N·NE·E·W·NW | P32: 830 | Q32: 310 | R32: 520 | AA32: http://www.paraglidingearth.com/?site=2918
A33: Aquitaine | B33: Pyrénées Atlantiques | C33: 64 | D33: 183 | E33: Issarbe | F33: Adison | G33: OK | H33: 1435 | I33: https://www.balisemeteo.com/balise.php?idBalise=183 | J33: 43.020599 | K33: -0.79958498 | L33: Issarbe | M33: 0.25 | P33: 1416 | Z33: Easy Access - drive up to the cross-country ski station - there is a building and parking opposite - the take off is just after the building and has windsocks and cleared area. | AA33: http://www.paraglidingearth.com/?site=21666 | AB33: Vu son emplacement voulu à proximité du décollage, au dessus de 40-50km/h, l'orientation de la direction peut être faussée par des "rouleaux" de vent météo (principalement par vent de sud).
A34: Aquitaine | B34: Pyrénées Atlantiques | C34: 64 | D34: 2336 | E34: La Rhune | F34: Openwindmap | G34: OK | H34: 864 | I34: https://www.balisemeteo.com/balise.php?idBalise=2336 | J34: 43.308456 | K34: -1.632848 | L34: aucun à <5 km | AB34: Informations non fiables remontées en date du 28/1/2020 Maintenance
A35: Auvergne | B35: Allier | C35: 03 | D35: 3520 | E35: Champbenest | F35: Openwindmap | G35: OK | H35: 352 | I35: https://www.balisemeteo.com/balise.php?idBalise=3520 | J35: 46.380127 | K35: 2.633713 | L35: aucun à <5 km
A36: Auvergne | B36: Allier | C36: 03 | D36: 5105 | E36: LE VERNET | F36: Openwindmap | G36: OK | H36: 428 | I36: https://www.balisemeteo.com/balise.php?idBalise=5105 | J36: 46.1022 | K36: 3.4556 | L36: aucun à <5 km
A37: Auvergne | B37: Allier | C37: 03 | D37: 5014 | E37: Loge des Gardes | F37: Holfuy | G37: OK | H37: 1101 | I37: https://www.balisemeteo.com/balise.php?idBalise=5014 | J37: 46.0047 | K37: 3.7942801 | L37: Laprugne Vol Libre | M37: 0.03 | P37: 1101 | AA37: http://www.paraglidingearth.com/?site=22046 | AB37: Décollage facile pas de rupture de pente. Atterrissage officiel un peu loin mais atterro "secours" a mi-distance. Site en Ouest idéalement ONO.
A38: Auvergne | B38: Cantal | C38: 15 | D38: 3613 | E38: Brezons | F38: Openwindmap | G38: OK | H38: 1242 | I38: https://www.balisemeteo.com/balise.php?idBalise=3613 | J38: 45.007131 | K38: 2.812402 | L38: Brezons | M38: 0.16 | N38: SW·W | O38: S·NW | P38: 1293 | Q38: 847 | R38: 446 | T38: oui | X38: Very strong thermals in summer._x000D_ _x000D_ Do not land above the cliff to the left of taking off. Dangerous. | Y38: Super thermical site. Cross possible without risks._x000D_ Very cool lift on evenings | Z38: Stop at the FFVL board on the side of the road coming from pratdebouc._x000D_ The take off is at the end of the trak, trough the fields._x000D_ _x000D_ Beware of the cows. | AA38: http://www.paraglidingearth.com/?site=2635
A39: Auvergne | B39: Cantal | C39: 15 | D39: 2571 | E39: Embec | F39: Openwindmap | G39: OK | H39: 1434 | I39: https://www.balisemeteo.com/balise.php?idBalise=2571 | J39: 45.161346 | K39: 2.771724 | L39: Dienne - pierre de labro | M39: 2.03 | N39: SE·S | P39: 1301 | AA39: http://www.paraglidingearth.com/?site=2633 | AB39: Site en E, SE ; turbulent en SO
A40: Auvergne | B40: Cantal | C40: 15 | D40: 2570 | E40: Engolneuf | F40: Openwindmap | G40: OK | H40: 1462 | I40: https://www.balisemeteo.com/balise.php?idBalise=2570 | J40: 45.132385 | K40: 2.789699 | L40: Col de serre | M40: 0.15 | N40: NW | P40: 1436 | AA40: http://www.paraglidingearth.com/?site=2632 | AB40: Site SO ; turbulent en SE
A41: Auvergne | B41: Cantal | C41: 15 | D41: 5071 | E41: Engolneuf | F41: Openwindmap | G41: En maintenance | H41: 2660 | I41: https://www.balisemeteo.com/balise.php?idBalise=5071 | J41: 45.132365 | K41: 2.789849 | L41: Col de serre | M41: 0.16 | N41: NW | P41: 1436 | AA41: http://www.paraglidingearth.com/?site=2632
A42: Auvergne | B42: Cantal | C42: 15 | D42: 177 | E42: Haut Cantal | F42: Adison | G42: OK | H42: 1667 | I42: https://www.balisemeteo.com/balise.php?idBalise=177 | J42: 45.118999 | K42: 2.6700001 | L42: Puy de la Tourte Ouest | M42: 0.05 | N42: W | O42: SW·NW | P42: 1651 | Q42: 992 | R42: 659 | T42: oui | U42: oui | AA42: http://www.paraglidingearth.com/?site=19234 | AB42: La balise est installée sur la crête qui amène au du Puy de la Tourte. Vent de secteur E-NE déco tourte E. Vent de secteur O-NO: déco tourte O.
A43: Auvergne | B43: Cantal | C43: 15 | D43: 176 | E43: Le Claux Chabraire | F43: Adison | G43: OK | H43: 1522 | I43: https://www.balisemeteo.com/balise.php?idBalise=176 | J43: 45.156799 | K43: 2.733 | L43: Chabraire | M43: 0.44 | N43: NW | O43: N·W | P43: 1552 | Q43: 1049 | R43: 503 | AA43: http://www.paraglidingearth.com/?site=2638
A44: Auvergne | B44: Cantal | C44: 15 | D44: 125 | E44: Plomb du Cantal | F44: Adison | G44: En maintenance | H44: 1804 | I44: https://www.balisemeteo.com/balise.php?idBalise=125 | J44: 45.062199 | K44: 2.7608299 | L44: Plomb du cantal | M44: 0.12 | N44: N·W·NW | P44: 1804 | Q44: 1238 | R44: 566 | S44: Station Super Lioran | T44: oui | AA44: http://www.paraglidingearth.com/?site=2637 | AB44: Les vols sur le domaine du Plomb du Cantal doivent s'effectuer dans le strict respect des consignes locales. Merci de votre compréhension. Bons vols !
A45: Auvergne | B45: Cantal | C45: 15 | D45: 3526 | E45: Près de Brezons | F45: Openwindmap | G45: En maintenance | H45: 580 | I45: https://www.balisemeteo.com/balise.php?idBalise=3526 | J45: 43.330944 | K45: 5.555384 | L45: Garlaban | M45: 0.06 | N45: E·SE·S | P45: 576 | Q45: 308 | R45: 268 | S45: Landing | T45: oui | U45: oui | W45: A prefectoral decree regulates access to the Bouches du Rhône mountains during the summer period from 1 June to 30 September. In the orange period access is free, in the red period it is limited between 6am and 11am, and in the black period any penetration is strictly prohibited and punishable by a contravention. Information on 0811 20 13 13 13 or on the website http://www.bouches-du-rhone.pref.gouv.fr/index.php Flights possible during the hunting season except on days when game is released (see calendar on the information panel on the website). The site is located in the TMA Marseille Provence 6 (ceiling limited to 1370 m altitude (4500 feet). | X45: General orientation: East to South. Dangerous in North, NW and NE winds and in Westerly winds. Favourable with easterly, east-south-easterly, south-south-easterly and south-south winds. In breezy conditions and in the absence of strong weather winds, flight is possible in the middle of the morning. However, the southwest sea breeze returns fairly quickly at midday, more or less early depending on the season due to the proximity of the sea, making flying turbulent and inadvisable. | Y45: Presence of a quiet area for the protection of the Bonelli's eagle. This area does not apply to the site for local flight. It is located 5km from the takeoff, in the municipality of Gémenos, heading east. This type of "upwind" flight is unlikely and of no interest. | Z45: On the A501 motorway linking Marseille to Aix en Provence via Aubagne, exit at exit 7, join the big roundabout and take the D96 for about a hundred metres. Then take the Chemin des Solans to a small roundabout where you have to turn left to stay on the Chemin des Solans. At the end of this road, at the end of the paved road, you will find a dirt DFCI track on the right that leads to a dirt parking with two large green tanks. This is where you should stop and consult the Site information panel. (Geographical coordinates of the car park: N43°19'27.67" / E 5°33'31.93"). Access to the decos is by foot, it takes about 40 minutes to walk. Access to the landing by vehicle is strictly prohibited. | AA45: http://www.paraglidingearth.com/?site=17227
A46: Auvergne | B46: Cantal | C46: 15 | D46: 3002 | E46: Redondet | F46: Openwindmap | G46: OK | H46: 1372 | I46: https://www.balisemeteo.com/balise.php?idBalise=3002 | J46: 45.102015 | K46: 2.660595 | L46: Puy mary - sud | M46: 0.26 | N46: S | P46: 1535 | Q46: 1027 | R46: 508 | S46: Liadouze | AA46: http://www.paraglidingearth.com/?site=2641
A47: Auvergne | B47: Cantal | C47: 15 | D47: 2525 | E47: VIC SUR CERE | F47: Openwindmap | G47: OK | H47: 1124 | I47: https://www.balisemeteo.com/balise.php?idBalise=2525 | J47: 44.980549 | K47: 2.659139 | L47: Vic sur cere | M47: 0.15 | N47: NW | P47: 1110 | Q47: 0 | R47: 1110 | T47: oui | AA47: http://www.paraglidingearth.com/?site=2636
A48: Auvergne | B48: Haute-Loire | C48: 43 | D48: 82 | E48: Chaspinhac | F48: Adison | G48: OK | H48: 905 | I48: https://www.balisemeteo.com/balise.php?idBalise=82 | J48: 45.1022 | K48: 3.92696 | L48: Chaspinhac | M48: 0.42 | N48: NE·E | P48: 855 | Q48: 642 | R48: 213 | X48: Wind info: http://www.balisemeteo.com/balise.php?idBalise=82 | Z48: From 'Chaspinhac' direction 'Malrevers-Beaulieu'. After 'Rouzeyroux, Le Roure' twice to the right (350m). | AA48: http://www.paraglidingearth.com/?site=2820
A49: Auvergne | B49: Haute-Loire | C49: 43 | D49: 3550 | E49: Chaudeyrolles | F49: Openwindmap | G49: OK | H49: 1381 | I49: https://www.balisemeteo.com/balise.php?idBalise=3550 | J49: 44.935666 | K49: 4.191968 | L49: Chaudeyrolles | M49: 0.04 | N49: N·NE | P49: 1380 | Q49: 1241 | R49: 139 | AA49: http://www.paraglidingearth.com/?site=2822
A50: Auvergne | B50: Haute-Loire | C50: 43 | D50: 3736 | E50: Conil | F50: Openwindmap | G50: OK | H50: 1120 | I50: https://www.balisemeteo.com/balise.php?idBalise=3736 | J50: 44.965553 | K50: 3.704965 | L50: Conil | M50: 0.05 | P50: 1090 | X50: https://www.openwindmap.org/windbird-1736 | Y50: Site thermique et technique, non recommandé aux débutants entre 11h et 17h | AA50: http://www.paraglidingearth.com/?site=23541 | AB50: Attention, site déconseillé aux débutants. Conditions thermiques parfois fortes. Atterrissages techniques
A51: Auvergne | B51: Haute-Loire | C51: 43 | D51: 5081 | E51: Mont Gerbizon | F51: Holfuy | G51: OK | H51: 1059 | I51: https://www.balisemeteo.com/balise.php?idBalise=5081 | J51: 45.188722 | K51: 4.000448 | L51: Gerbizon NE | M51: 0.02 | P51: 1061 | X51: https://holfuy.com/fr/weather/1332 | Y51: Plus haut dénivelé de Haute-Loire (564m). ~1h30 de marche depuis la piscine de Retournac. | Z51: Se garer à la 1ère clairière, monter par le sentier de sous bois. | AA51: http://www.paraglidingearth.com/?site=23540
A52: Auvergne | B52: Haute-Loire | C52: 43 | D52: 5082 | E52: St Berain 43 | F52: Holfuy | G52: OK | H52: 987 | I52: https://www.balisemeteo.com/balise.php?idBalise=5082 | J52: 45.018084 | K52: 3.640297 | L52: Saint-Bérain | M52: 0.2 | N52: SW·W | P52: 1069 | AA52: http://www.paraglidingearth.com/?site=22921
A53: Auvergne | B53: Puy-De-Dôme | C53: 63 | D53: 1011 | E53: Corent | F53: Holfuy | G53: OK | H53: 600 | I53: https://www.balisemeteo.com/balise.php?idBalise=1011 | J53: 45.65918 | K53: 3.17944 | L53: Puy de corent | M53: 0.34 | N53: SE·S·SW·W·NW | P53: 558 | AA53: http://www.paraglidingearth.com/?site=2902 | AB53: La balise est située sur le déco Sud/Sud-Ouest, elle a donc tendance à minimiser le vent en secteur Ouest. Attention par vent de Sud, risque d'accélération rapide. Turbulent par O et NO fort. Décollage NO technique. Pas d'atterrissage officiel. Accord avec les chasseurs en période de chasse. Atterrissage tournant suivant culture, nombreuses jachères. Atterrissage facile sur les chemins, toutes expositions. Repose au sommet aisée. Réglementation aérienne : Site situé dans la TMA 1 de Clermont-Aulnat, altitude maximum autorisée 300m/sol ou 820m/mer
A54: Auvergne | B54: Puy-De-Dôme | C54: 63 | D54: 2047 | E54: Le Cornillon - Job | F54: Openwindmap | G54: OK | H54: 1130 | I54: https://www.balisemeteo.com/balise.php?idBalise=2047 | J54: 45.637631 | K54: 3.753356 | L54: job-ambert Cornillon | M54: 0.02 | N54: W·NW | O54: N·SW | P54: 1123 | T54: oui | Y54: the town council seams to had big effort to do a free-flying stadium. | Z54: from \'Ambert\' go to the north during 3 km on the road D906. Turn on the right (D66 road) and cross \'La Forie\' village. Stay on this road and cross \'Job\'. Go to the neck \'col de Chansert\' and follow the sign \'site de vol-libre\'._x000D_ Before the neck turn on your left to take a track with the sign \'dÃ©collage du Cornillon\'. Follow this sign during +-2km. You can parc your car near the take off :-) | AA54: http://www.paraglidingearth.com/?site=6862 | AB54: Orientation du site NO / O Dénivelé: 550m. TMA la semaine 2590m TMA le week-end 2890m
A55: Auvergne | B55: Puy-De-Dôme | C55: 63 | D55: 30 | E55: Mt Chouvé Job Ambert | F55: Adison | G55: OK | H55: 1462 | I55: https://www.balisemeteo.com/balise.php?idBalise=30 | J55: 45.630969 | K55: 3.781301 | L55: Job-ambert Mont Chouve | M55: 0.02 | N55: S·SW·W·NW | P55: 1414 | T55: oui | X55: good informations: http://www.balisemeteo.com/balise.php?idBalise=30 | Z55: from 'Ambert' go to the north during 3 km on the road D906. Turn on the right (D66 road) and cross 'La Forie' village. Stay on this road and cross 'Job'. Go to the pass 'col de Chansert' and follow the sign 'site de vol-libre'._x000D_ On the pass turn on your right to take a track with the sign 'decollage Mont Chouve'. Follow the signs. | AA55: http://www.paraglidingearth.com/?site=2905 | AB55: Dénivelé décollage/atterrissage 850m. TMA la semaine 2590m TMA le week-end 2890m
A56: Auvergne | B56: Puy-De-Dôme | C56: 63 | D56: 2486 | E56: Pic d'Ysson | F56: Openwindmap | G56: En maintenance | H56: 850 | I56: https://www.balisemeteo.com/balise.php?idBalise=2486 | J56: 45.545288 | K56: 3.0395 | L56: Saurier | M56: 2.39 | N56: N·NE·SE·S·W·NW | P56: 892 | AA56: http://www.paraglidingearth.com/?site=2897 | AB56: Décollage possible toutes orientations sauf E/NE
A57: Auvergne | B57: Puy-De-Dôme | C57: 63 | D57: 1010 | E57: Puy de Dôme Nord | F57: Holfuy | G57: OK | H57: 1450 | I57: https://www.balisemeteo.com/balise.php?idBalise=1010 | J57: 45.77302 | K57: 2.96437 | L57: Puy de Dome | M57: 0.15 | N57: N·NE·E·SE·S·SW·W·NW | P57: 1422 | Q57: 897 | R57: 525 | T57: oui | W57: ATTN: CTR/ TMA (Clermont) very close to the east! | X57: Wind info: http://www.balisemeteo.com/balise.php?idBalise=46_x000D_ Webcam: http://wwwobs.univ-bpclermont.fr/opgc/webcam.php | Y57: Apparently for french pilots you must have the pilot diploma. It's a prefet order._x000D_ You have to wear a helmet too. | Z57: Cog wheel train: http://www.panoramiquedesdomes.fr/_x000D_ From june to september (10h-19h) car forbiden. Take the shuttle: 2,30 euros (paraglider price)._x000D_ before this dates and if the road is open, 4 euros to go up with your car. | AA57: http://www.paraglidingearth.com/?site=2896 | AB57: Description : Forte fréquentation du site les WE et en été ! Attention au câble d'alimentation du train tout autour du site. Attention lors de votre approche à l'atterrissage de la Taillerie à ne pas survoler trop bas la gare ainsi que le câble, risque de fort gradient. Atterrissage de la Taillerie pouvant aussi être très turbulent. Réglementation aérienne : Site situé dans la TMA 5.1 de Clermont-Aulnat. Attention à vous renseigner sur les TMA proches pour de vos vols de distance. CTR très proche à l'est du PDD. Atterrissage dans le Grand champ situé derrière la gare de départ du Panoramique: très turbulent l'après-midi en conditions thermiques - Fort gradient. Attention à ne pas survoler la gare et le câble trop bas lors de votre approche. Site très fréquenté, attention lors d'arrivées simultanées. Situé en TMA 2.3 de Clermont-Aulnat. CTR proche en direction de Clermont-Ferrand. Atterrissage Ouest : Pré tout en longueur au milieu d'une foret. Terrain enclavé au milieu des sapins, attention à bien soigner son approche finale. Atterrissage pouvant être très turbulent par vent de NO. Attention au risque d'inversion en fin de soirée, la brise pouvant descendre du col. Restrictions : Attention en présence de moutons à bien respecter les zones délimitées. Ne pas se garer sur le terrain.
A58: Auvergne | B58: Puy-De-Dôme | C58: 63 | D58: 1004 | E58: Puy de la Tache | F58: Holfuy | G58: OK | H58: 1615 | I58: https://www.balisemeteo.com/balise.php?idBalise=1004 | J58: 45.592105 | K58: 2.845077 | L58: Puy de la tache | M58: 0.04 | N58: N·NE | P58: 1606 | Q58: 1396 | R58: 210 | AA58: http://www.paraglidingearth.com/?site=2911 | AB58: Site idéalement orienté N/NE/E, volable aussi par SE faible et par vent d'O/NO. Marche d'accès au déco: entre 20' et 30'depuis le col de la Croix Morand.
A59: Auvergne | B59: Puy-De-Dôme | C59: 63 | D59: 151 | E59: Puy Saint Romain | F59: Adison | G59: OK | H59: 780 | I59: https://www.balisemeteo.com/balise.php?idBalise=151 | J59: 45.679903 | K59: 3.242922 | L59: Puy de st romain | M59: 0.29 | N59: S·SW·W | P59: 708 | AA59: http://www.paraglidingearth.com/?site=2894 | AB59: Décollage toutes orientations possible sauf en NE. Site situé dans la TMA 1 de Clermont-Fd. Altitude autorisée 300m/sol ou 820m/mer.
A60: Auvergne | B60: Puy-De-Dôme | C60: 63 | D60: 46 | E60: Saurier-Creste | F60: Adison | G60: OK | H60: 870 | I60: https://www.balisemeteo.com/balise.php?idBalise=46 | J60: 45.545587 | K60: 3.03967 | L60: Saurier | M60: 2.41 | N60: N·NE·SE·S·W·NW | P60: 892 | AA60: http://www.paraglidingearth.com/?site=2897 | AB60: Décollage possible aussi en N / NO
A61: Auvergne | B61: Puy-De-Dôme | C61: 63 | D61: 1003 | E61: St Sandoux | F61: Holfuy | G61: OK | H61: 780 | I61: https://www.balisemeteo.com/balise.php?idBalise=1003 | J61: 45.6317 | K61: 3.1164 | L61: Croix de st sandoux | M61: 0.07 | N61: N·NE | P61: 786 | Q61: 522 | R61: 264 | T61: oui | U61: oui | AA61: http://www.paraglidingearth.com/?site=2893 | AB61: 2 décos orientés N & E, site très fréquenté, soyez vigilants !
A62: Auvergne | B62: Puy-De-Dôme | C62: 63 | D62: 1002 | E62: Valbeleix | F62: Holfuy | G62: OK | H62: 1180 | I62: https://www.balisemeteo.com/balise.php?idBalise=1002 | J62: 45.4667 | K62: 2.9978 | L62: Valbeleix | M62: 0 | N62: N·SW·W·NW | P62: 1153 | AA62: http://www.paraglidingearth.com/?site=2898 | AB62: Site orienté SO/O, magnifique site à soaring !
A63: Basse Normandie | B63: Calvados | C63: 14 | D63: 158 | E63: Commes | F63: Adison | G63: OK | H63: 70 | I63: https://www.balisemeteo.com/balise.php?idBalise=158 | J63: 49.3468 | K63: -0.7123 | L63: Commes | M63: 0.96 | N63: N·NE | P63: 60 | Q63: 60 | AA63: http://www.paraglidingearth.com/?site=2613
A64: Basse Normandie | B64: Calvados | C64: 14 | D64: 96 | E64: Houlgate | F64: Adison | G64: OK | H64: 5 | I64: https://www.balisemeteo.com/balise.php?idBalise=96 | J64: 49.301399 | K64: -0.082222 | L64: Villers sur mer | M64: 4.95 | N64: N·NW | P64: 64 | Q64: 20 | R64: 44 | U64: oui | Y64: xx | Z64: ATTENTION SITE FERME SUITE GLISSEMENT DE TERRAIN AU DECOLLAGE NE PAS Y VOLER | AA64: http://www.paraglidingearth.com/?site=2611
A65: Basse Normandie | B65: Calvados | C65: 14 | D65: 6093 | E65: La Roche à Bunel | F65: Holfuy | G65: OK | H65: 115 | I65: https://www.balisemeteo.com/balise.php?idBalise=6093 | J65: 48.9931 | K65: -0.4987 | L65: La Roche a Bunel | M65: 0.02 | N65: E | O65: SE | P65: 101 | Q65: 21 | R65: 80 | T65: oui | U65: oui | X65: in summer, very turbulent if many thermals | Y65: for pilots with experience | AA65: http://www.paraglidingearth.com/?site=2610
A66: Basse Normandie | B66: Calvados | C66: 14 | D66: 122 | E66: Saint Omer | F66: Adison | G66: OK | H66: 264 | I66: https://www.balisemeteo.com/balise.php?idBalise=122 | J66: 48.931099 | K66: -0.44328299 | L66: Le mont du pere | M66: 0.14 | N66: SE·NW | P66: 266 | Y66: School slope | AA66: http://www.paraglidingearth.com/?site=2616
A67: Basse Normandie | B67: Calvados | C67: 14 | D67: 2352 | E67: St-Marc d'Ouilly | F67: Openwindmap | G67: OK | H67: 178 | I67: https://www.balisemeteo.com/balise.php?idBalise=2352 | J67: 48.882092 | K67: -0.44597 | L67: St Marc d'Ouilly | M67: 0.08 | N67: NE | O67: N | P67: 181 | Q67: 49 | R67: 132 | T67: oui | U67: oui | AA67: http://www.paraglidingearth.com/?site=2614
A68: Basse Normandie | B68: Calvados | C68: 14 | D68: 97 | E68: Vierville-sur-mer | F68: Adison | G68: OK | H68: 40 | I68: https://www.balisemeteo.com/balise.php?idBalise=97 | J68: 49.38189 | K68: -0.908735 | L68: Vierville sur mer | M68: 0.17 | N68: NE | P68: 39 | AA68: http://www.paraglidingearth.com/?site=2612
A69: Basse Normandie | B69: Calvados | C69: 14 | D69: 2562 | E69: Villers sur Mer | F69: Openwindmap | G69: En maintenance | H69: 4 | I69: https://www.balisemeteo.com/balise.php?idBalise=2562 | J69: 49.321927 | K69: -0.011983 | L69: Villers sur mer | M69: 0.64 | N69: N·NW | P69: 64 | Q69: 20 | R69: 44 | U69: oui | Y69: xx | Z69: ATTENTION SITE FERME SUITE GLISSEMENT DE TERRAIN AU DECOLLAGE NE PAS Y VOLER | AA69: http://www.paraglidingearth.com/?site=2611 | AB69: Je suis perchée sur un mat au dessus du drapeau à côté du club nautique de Villers. J'appartiens au club Voiles Libres Pays d'Auge.
A70: Basse Normandie | B70: Manche | C70: 50 | D70: 3464 | E70: Carolles | F70: Openwindmap | G70: OK | H70: 46 | I70: https://www.balisemeteo.com/balise.php?idBalise=3464 | J70: 48.755743 | K70: -1.573155 | L70: Carolles | M70: 0.14 | N70: W·NW | P70: 57 | Q70: 4 | R70: 53 | U70: oui | AA70: http://www.paraglidingearth.com/?site=2851
A71: Basse Normandie | B71: Manche | C71: 50 | D71: 3449 | E71: Champeaux | F71: Openwindmap | G71: OK | H71: 23 | I71: https://www.balisemeteo.com/balise.php?idBalise=3449 | J71: 48.732668 | K71: -1.539414 | L71: Carolles | M71: 3.44 | N71: W·NW | P71: 57 | Q71: 4 | R71: 53 | U71: oui | AA71: http://www.paraglidingearth.com/?site=2851
A72: Basse Normandie | B72: Manche | C72: 50 | D72: 3502 | E72: Le Roc | F72: Openwindmap | G72: OK | H72: 35 | I72: https://www.balisemeteo.com/balise.php?idBalise=3502 | J72: 48.836246 | K72: -1.610457 | L72: Donville | M72: 1.79 | N72: N·NW | P72: 25 | Y72: initialy imported from DHV XC Contest Leonardo | AA72: http://www.paraglidingearth.com/?site=18735
A73: Basse Normandie | B73: Manche | C73: 50 | D73: 2334 | E73: Les Roches de Ham | F73: Openwindmap | G73: OK | H73: 23 | I73: https://www.balisemeteo.com/balise.php?idBalise=2334 | J73: 49.026481 | K73: -1.040949 | L73: aucun à <5 km
A74: Basse Normandie | B74: Manche | C74: 50 | D74: 1014 | E74: Omonville | F74: Holfuy | G74: OK | H74: 90 | I74: https://www.balisemeteo.com/balise.php?idBalise=1014 | J74: 49.69557 | K74: -1.83532 | L74: Omonville la rogue | M74: 0.17 | N74: NE | P74: 90 | U74: oui | AA74: http://www.paraglidingearth.com/?site=2853 | AB74: Balise du site d'Omonville la rogue orientation Est
A75: Basse Normandie | B75: Manche | C75: 50 | D75: 1013 | E75: Pointe de la Hague | F75: Holfuy | G75: OK | H75: 90 | I75: https://www.balisemeteo.com/balise.php?idBalise=1013 | J75: 49.69433 | K75: -1.93354 | L75: Ecalgrain | M75: 0.02 | N75: W | P75: 99 | U75: oui | AA75: http://www.paraglidingearth.com/?site=11496 | AB75: Balise du Site d'Ecalgrain orientation ouest
A76: Basse Normandie | B76: Manche | C76: 50 | D76: 81 | E76: Vauville | F76: Holfuy | G76: OK | H76: 137 | I76: https://www.balisemeteo.com/balise.php?idBalise=81 | J76: 49.62419 | K76: -1.82904 | L76: Dunes de Biville | M76: 1.94 | O76: SW·W | P76: 7 | AA76: http://www.paraglidingearth.com/?site=22885 | AB76: Balise de Site des Pierres Pouquelées orientation sud ouest
A77: Bourgogne | B77: Côte d'Or | C77: 21 | D77: 2546 | E77: Balise Mobile | F77: Openwindmap | G77: OK | H77: 563 | I77: https://www.balisemeteo.com/balise.php?idBalise=2546 | J77: 47.05329 | K77: 4.732107 | L77: Meloisey | M77: 1.64 | N77: SE | O77: S | P77: 510 | T77: oui | U77: oui | AA77: http://www.paraglidingearth.com/?site=2673 | AB77: Balise mobile Belair Parapente
A78: Bourgogne | B78: Côte d'Or | C78: 21 | D78: 152 | E78: Baulme la Roche | F78: Openwindmap | G78: OK | H78: 542 | I78: https://www.balisemeteo.com/balise.php?idBalise=152 | J78: 47.35018 | K78: 4.800312 | L78: Baulme la Roche | M78: 0.19 | N78: SW | P78: 559 | Q78: 414 | R78: 145 | T78: oui | U78: oui | AA78: http://www.paraglidingearth.com/?site=9333
A79: Bourgogne | B79: Côte d'Or | C79: 21 | D79: 2200 | E79: Bligny sur Ouche | F79: Openwindmap | G79: OK | H79: 523 | I79: https://www.balisemeteo.com/balise.php?idBalise=2200 | J79: 47.114608 | K79: 4.675628 | L79: Bligny-sur-Ouche | M79: 0.01 | O79: W·NW | P79: 513 | AA79: http://www.paraglidingearth.com/?site=23703 | AB79: Déco de Bligny sur Ouche, voir fiche site. Défavorable par vent de sud et vent de nord.
A80: Bourgogne | B80: Côte d'Or | C80: 21 | D80: 2954 | E80: Bligny sur Ouche | F80: Openwindmap | G80: En maintenance | H80: 495 | I80: https://www.balisemeteo.com/balise.php?idBalise=2954 | J80: 47.114633 | K80: 4.675622 | L80: Bligny-sur-Ouche | M80: 0.02 | O80: W·NW | P80: 513 | AA80: http://www.paraglidingearth.com/?site=23703
A81: Bourgogne | B81: Côte d'Or | C81: 21 | D81: 2242 | E81: Chatillon / Seine | F81: Openwindmap | G81: En maintenance | H81: 265 | I81: https://www.balisemeteo.com/balise.php?idBalise=2242 | J81: 47.848854 | K81: 4.579119 | L81: aucun à <5 km | AB81: Cette balise Pioupiou appartient à l'aéro-club du pays Chatillonnais. Elle est située sur le toit du hangar avion de l'aérodrome, son gestionnaire et responsable est Daniel, pilote et administrateur de l'aéro-club et pilote parapente au sein du club des aigles de tonnerre.
A82: Bourgogne | B82: Côte d'Or | C82: 21 | D82: 2281 | E82: Dampierre et Flée | F82: Openwindmap | G82: En maintenance | H82: 254 | I82: https://www.balisemeteo.com/balise.php?idBalise=2281 | J82: 47.475668 | K82: 5.357368 | L82: aucun à <5 km
A83: Bourgogne | B83: Côte d'Or | C83: 21 | D83: 2955 | E83: Falaise de Meloisey | F83: Openwindmap | G83: OK | H83: 562 | I83: https://www.balisemeteo.com/balise.php?idBalise=2955 | J83: 47.038206 | K83: 4.722808 | L83: Meloisey | M83: 0.24 | N83: SE | O83: S | P83: 510 | T83: oui | U83: oui | AA83: http://www.paraglidingearth.com/?site=2673
A84: Bourgogne | B84: Côte d'Or | C84: 21 | D84: 2938 | E84: Reullée | F84: Openwindmap | G84: OK | H84: 190 | I84: https://www.balisemeteo.com/balise.php?idBalise=2938 | J84: 47.007834 | K84: 4.947867 | L84: aucun à <5 km
A85: Bourgogne | B85: Côte d'Or | C85: 21 | D85: 5100 | E85: Savigny sous Malain | F85: Openwindmap | G85: OK | H85: 560 | I85: https://www.balisemeteo.com/balise.php?idBalise=5100 | J85: 47.338709 | K85: 4.7511145 | L85: savigny sous malain | M85: 0.26 | N85: S | O85: SE·SW | P85: 531 | Q85: 518 | R85: 13 | T85: oui | AA85: http://www.paraglidingearth.com/?site=9735 | AB85: présentation : https://youtu.be/ucT3WaLbkC4
A86: Bourgogne | B86: Côte d'Or | C86: 21 | D86: 2919 | E86: Trois Croix | F86: Openwindmap | G86: OK | H86: 462 | I86: https://www.balisemeteo.com/balise.php?idBalise=2919 | J86: 46.917667 | K86: 4.671622 | L86: les trois croix | M86: 0.27 | N86: NE·SE | P86: 505 | Q86: 486 | R86: 19 | T86: oui | U86: oui | AA86: http://www.paraglidingearth.com/?site=9736 | AB86: Situé au bord de la falaise, sous le décollage.
A87: Bourgogne | B87: Côte d'Or | C87: 21 | D87: 5099 | E87: Velars sur Ouche | F87: Openwindmap | G87: OK | H87: 540 | I87: https://www.balisemeteo.com/balise.php?idBalise=5099 | J87: 47.301636 | K87: 4.9004195 | L87: Velars sur Ouches | M87: 0.02 | N87: E·W | O87: NE | P87: 536 | Q87: 411 | R87: 125 | T87: oui | AA87: http://www.paraglidingearth.com/?site=9332 | AB87: Déco Est et Ouest. Balise sur le déco Est et sous le vent de l'Ouest. Site géré par les Ailes de Bourgogne https://www.lesailesdebourgogne.fr/
A88: Bourgogne | B88: Côte d'Or | C88: 21 | D88: 2953 | E88: Villars-Fontaine | F88: Openwindmap | G88: OK | H88: 554 | I88: https://www.balisemeteo.com/balise.php?idBalise=2953 | J88: 47.149706 | K88: 4.898069 | L88: aucun à <5 km
A89: Bourgogne | B89: Saône et Loire | C89: 71 | D89: 2366 | E89: Cluny Montaudon | F89: Openwindmap | G89: OK | H89: 437 | I89: https://www.balisemeteo.com/balise.php?idBalise=2366 | J89: 46.445173 | K89: 4.628466 | L89: Montaudon -Plaisir | M89: 0.06 | P89: 438 | AA89: http://www.paraglidingearth.com/?site=22020
A90: Bourgogne | B90: Saône et Loire | C90: 71 | D90: 3441 | E90: La Pierre Levée | F90: Openwindmap | G90: OK | H90: 324 | I90: https://www.balisemeteo.com/balise.php?idBalise=3441 | J90: 46.540679 | K90: 4.783396 | L90: La pierre levée | M90: 0.04 | N90: NW | O90: W | P90: 326 | Q90: 277 | R90: 49 | T90: oui | U90: oui | AA90: http://www.paraglidingearth.com/?site=19843
A91: Bourgogne | B91: Saône et Loire | C91: 71 | D91: 2225 | E91: la Vierge - Varanges | F91: Openwindmap | G91: OK | H91: 472 | I91: https://www.balisemeteo.com/balise.php?idBalise=2225 | J91: 46.460162 | K91: 4.717266 | L91: La vierge | M91: 0.01 | N91: W | P91: 466 | Q91: 407 | R91: 59 | T91: oui | U91: oui | AA91: http://www.paraglidingearth.com/?site=19840 | AB91: Cette balise, installée par le CDVL71 se situe sur un décollage orienté ouest à ouest nord ouest. Les informations plus précises sur se site de vol sont données sur le panneau d'information situé sur le parking au pied du décollage.
A92: Bourgogne | B92: Saône et Loire | C92: 71 | D92: 2922 | E92: Monsard | F92: Openwindmap | G92: En maintenance | H92: 397 | I92: https://www.balisemeteo.com/balise.php?idBalise=2922 | J92: 46.345736 | K92: 4.707059 | L92: Montsard | M92: 0.24 | N92: N | P92: 364 | Q92: 326 | R92: 38 | Y92: Site trÃ¨s petit, lignes Ã©lectriques Ã mi pente. Ne pas voler en retrait de la ligne de falaise._x000D_ Pas de pente Ã©cole Ã l'atterrissage. Vaches toute l'annÃ©e._x000D_ _x000D_ LE MONT SARD. Orientation : Nord. DÃ©nivelÃ© : 70 m. On y monte en voiture. DÃ©collage falaise, minuscule. Une seule voile Ã©talÃ©e Ã la fois. Ce site dispose d'un des meilleurs rendements du coin. L'atterrissage est situÃ© au pied, lÃ oÃ¹ il y a des vaches. La repose au dÃ©collage est possible, mais trÃ¨s technique. C'est de lÃ que les premiers vols ont Ã©tÃ© effectuÃ©s dans la rÃ©gion, en 1985. | AA92: http://www.paraglidingearth.com/?site=2977 | AB92: Site du Monsard à Bussières. Décollage parapente en N, exploitable de NNE à NO. Plus d'info ici : http://federation.ffvl.fr/sites_pratique/voir/428 Le site est géré par "Cluny s'envole".
A93: Bourgogne | B93: Saône et Loire | C93: 71 | D93: 2962 | E93: Mont Dardon à Uxeau 488m | F93: Openwindmap | G93: OK | H93: 495 | I93: https://www.balisemeteo.com/balise.php?idBalise=2962 | J93: 46.67712 | K93: 4.03675 | L93: Mont Dardon Sud | M93: 0.05 | N93: S | P93: 495 | Q93: 356 | R93: 139 | S93: null | Y93: Do not fly when the wind come from SE: big rolls, due to vegetals. Le meilleur rendement de ce site est sur NO | AA93: http://www.paraglidingearth.com/?site=2973
A94: Bourgogne | B94: Saône et Loire | C94: 71 | D94: 3458 | E94: Mont Péjus | F94: Openwindmap | G94: OK | H94: 338 | I94: https://www.balisemeteo.com/balise.php?idBalise=3458 | J94: 46.5956 | K94: 4.639523 | L94: Mont pejus | M94: 0.02 | N94: SE·S | P94: 339 | Q94: 236 | R94: 103 | U94: oui | AA94: http://www.paraglidingearth.com/?site=19845
A95: Bourgogne | B95: Saône et Loire | C95: 71 | D95: 135 | E95: Moroges | F95: Adison | G95: OK | H95: 468 | I95: https://www.balisemeteo.com/balise.php?idBalise=135 | J95: 46.736401 | K95: 4.6652799 | L95: moroges | M95: 0.33 | N95: N·NE | P95: 431 | Q95: 354 | R95: 77 | T95: oui | U95: oui | AA95: http://www.paraglidingearth.com/?site=19354
A96: Bourgogne | B96: Saône et Loire | C96: 71 | D96: 2374 | E96: Moroges | F96: Openwindmap | G96: OK | H96: 273 | I96: https://www.balisemeteo.com/balise.php?idBalise=2374 | J96: 46.748585 | K96: 4.683851 | L96: moroges | M96: 1.64 | N96: N·NE | P96: 431 | Q96: 354 | R96: 77 | T96: oui | U96: oui | AA96: http://www.paraglidingearth.com/?site=19354
A97: Bourgogne | B97: Saône et Loire | C97: 71 | D97: 3505 | E97: Roche Vergisson Sud | F97: Openwindmap | G97: OK | H97: 417 | I97: https://www.balisemeteo.com/balise.php?idBalise=3505 | J97: 46.31395 | K97: 4.716561 | L97: Vergission S-SO | M97: 0.07 | N97: S·SW | P97: 455 | Q97: 391 | R97: 64 | T97: oui | U97: oui | AA97: http://www.paraglidingearth.com/?site=19838
A98: Bourgogne | B98: Saône et Loire | C98: 71 | D98: 65 | E98: Signal d'Uchon | F98: Adison | G98: OK | H98: 640 | I98: https://www.balisemeteo.com/balise.php?idBalise=65 | J98: 46.813 | K98: 4.2580299 | L98: Uchon | M98: 0.84 | N98: W·NW | P98: 643 | Q98: 381 | R98: 262 | T98: oui | U98: oui | W98: Below TMA St.Yan: Mnax: 600m/gnd - 2000m/asl | X98: North winds | Z98: T.O. parking coordinates: 46.806338N;4.256098E | AA98: http://www.paraglidingearth.com/?site=2974 | AB98: Orientation du site Nord Ouest. Balise déventée par vents de Nord-Est , Sud-Est et Sud
A99: Bourgogne | B99: Saône et Loire | C99: 71 | D99: 189 | E99: Signal Mère Boîtier | F99: Adison | G99: OK | H99: 758 | I99: https://www.balisemeteo.com/balise.php?idBalise=189 | J99: 46.302514 | K99: 4.6322 | L99: En cours d'ouverture | M99: 0.57 | P99: 609 | AA99: http://www.paraglidingearth.com/?site=22027 | AB99: Point dominant sans site de décollage à la balise - Sites de proximité à vol d'oiseau: Champvent (SO-O) à 500 m à l'Ouest, Chavannes ( S-SO) à 1 km au sud et de Fontaine Verdine ( O-NO) à 5 km à l'Ouest Comme pas mal de balises, aux grands froids humides, elle est bloquée. Voir le site de la balise: https://www.aircluny.fr/web_images/balise_smb__web.jpg
A100: Bourgogne | B100: Saône et Loire | C100: 71 | D100: 3443 | E100: Suin | F100: Openwindmap | G100: OK | H100: 598 | I100: https://www.balisemeteo.com/balise.php?idBalise=3443 | J100: 46.433946 | K100: 4.476097 | L100: Butte de Suin | M100: 0.09 | P100: 585 | AA100: http://www.paraglidingearth.com/?site=22026
...

Sheet Synthèse
A1: Synthèse par région
A3: Région | B3: Nb balises | C3: Avec spot <5 km
A4: Alsace | B4: =COUNTIF(Balises!A:A,A4) -> 21 | C4: =COUNTIFS(Balises!A:A,A4,Balises!L:L,"<>aucun à <5 km") -> 12
A5: Aquitaine | B5: =COUNTIF(Balises!A:A,A5) -> 12 | C5: =COUNTIFS(Balises!A:A,A5,Balises!L:L,"<>aucun à <5 km") -> 10
A6: Auvergne | B6: =COUNTIF(Balises!A:A,A6) -> 28 | C6: =COUNTIFS(Balises!A:A,A6,Balises!L:L,"<>aucun à <5 km") -> 26
A7: Basse Normandie | B7: =COUNTIF(Balises!A:A,A7) -> 14 | C7: =COUNTIFS(Balises!A:A,A7,Balises!L:L,"<>aucun à <5 km") -> 13
A8: Bourgogne | B8: =COUNTIF(Balises!A:A,A8) -> 30 | C8: =COUNTIFS(Balises!A:A,A8,Balises!L:L,"<>aucun à <5 km") -> 24
A9: Bretagne | B9: =COUNTIF(Balises!A:A,A9) -> 15 | C9: =COUNTIFS(Balises!A:A,A9,Balises!L:L,"<>aucun à <5 km") -> 14
A10: Centre | B10: =COUNTIF(Balises!A:A,A10) -> 1 | C10: =COUNTIFS(Balises!A:A,A10,Balises!L:L,"<>aucun à <5 km") -> 0
A11: Champagne-Ardenne | B11: =COUNTIF(Balises!A:A,A11) -> 18 | C11: =COUNTIFS(Balises!A:A,A11,Balises!L:L,"<>aucun à <5 km") -> 15
A12: Corse | B12: =COUNTIF(Balises!A:A,A12) -> 9 | C12: =COUNTIFS(Balises!A:A,A12,Balises!L:L,"<>aucun à <5 km") -> 7
A13: Franche-Comté | B13: =COUNTIF(Balises!A:A,A13) -> 37 | C13: =COUNTIFS(Balises!A:A,A13,Balises!L:L,"<>aucun à <5 km") -> 32
A14: Haute Normandie | B14: =COUNTIF(Balises!A:A,A14) -> 12 | C14: =COUNTIFS(Balises!A:A,A14,Balises!L:L,"<>aucun à <5 km") -> 11
A15: Ile de France | B15: =COUNTIF(Balises!A:A,A15) -> 3 | C15: =COUNTIFS(Balises!A:A,A15,Balises!L:L,"<>aucun à <5 km") -> 1
... A26: Outre Mer | B26: =COUNTIF(Balises!A:A,A26) -> 10 | C26: =COUNTIFS(Balises!A:A,A26,Balises!L:L,"<>aucun à <5 km") -> 7
A27: TOTAL | B27: =SUM(B4:B26) -> 634 | C27: =SUM(C4:C26) -> 516
A29: Source : balisemeteo.com (relevé du 15/07/2026) croisé avec Paragliding Earth (site de vol le plus proche dans un rayon de 5 km — données contributives, à recouper avec les fiches FFVL avant de voler).
